stac_api/__init__.py
stac_api/app.py
stac_api/config.py
stac_api/errors.py
stac_api/openapi.py
stac_api/api/__init__.py
stac_api/api/app.py
stac_api/api/middleware.py
stac_api/api/models.py
stac_api/api/routes.py
stac_api/api/extensions/__init__.py
stac_api/api/extensions/context.py
stac_api/api/extensions/extension.py
stac_api/api/extensions/fields.py
stac_api/api/extensions/query.py
stac_api/api/extensions/sort.py
stac_api/api/extensions/tiles.py
stac_api/api/extensions/transaction.py
stac_api/clients/__init__.py
stac_api/clients/base.py
stac_api/clients/postgres/__init__.py
stac_api/clients/postgres/core.py
stac_api/clients/postgres/session.py
stac_api/clients/postgres/tokens.py
stac_api/clients/postgres/transactions.py
stac_api/clients/tiles/__init__.py
stac_api/clients/tiles/ogc.py
stac_api/models/__init__.py
stac_api/models/database.py
stac_api/models/decompose.py
stac_api/models/links.py
stac_api/models/ogc.py
stac_api/models/schemas.py
tests/api/__init__.py
tests/api/test_api.py
tests/clients/__init__.py
tests/clients/test_postgres.py
tests/resources/__init__.py
tests/resources/test_collection.py
tests/resources/test_conformance.py
tests/resources/test_item.py
tests/resources/test_mgmt.py
arturo_stac_api-1.1.0.dist-info/LICENSE
arturo_stac_api-1.1.0.dist-info/METADATA
arturo_stac_api-1.1.0.dist-info/WHEEL
arturo_stac_api-1.1.0.dist-info/top_level.txt
arturo_stac_api-1.1.0.dist-info/RECORD
