Metadata-Version: 2.1
Name: arturo-stac-api
Version: 1.1.0
Summary: Arturo's STAC compliant API implementation
Home-page: https://github.com/arturo-ai/arturo-stac-api
Author: Arturo Engineering
Author-email: engineering@arturo.ai
License: MIT
Keywords: STAC FastAPI COG
Platform: UNKNOWN
Classifier: Intended Audience :: Developers
Classifier: Intended Audience :: Information Technology
Classifier: Intended Audience :: Science/Research
Classifier: Programming Language :: Python :: 3.8
Classifier: License :: OSI Approved :: MIT License
Requires-Python: >=3.8
Requires-Dist: attrs
Requires-Dist: uvicorn[standard]
Requires-Dist: gunicorn
Requires-Dist: fastapi (>=0.60.0)
Requires-Dist: alembic
Requires-Dist: psycopg2-binary
Requires-Dist: shapely
Requires-Dist: sqlalchemy
Requires-Dist: geoalchemy2 (<0.8.0)
Requires-Dist: sqlakeyset
Requires-Dist: stac-pydantic (>=1.3.5)
Requires-Dist: pydantic[dotenv]
Requires-Dist: titiler (==0.1.0a12)
Requires-Dist: fastapi-utils
Provides-Extra: dev
Requires-Dist: pytest ; extra == 'dev'
Requires-Dist: pytest-cov ; extra == 'dev'
Requires-Dist: pytest-asyncio ; extra == 'dev'
Requires-Dist: pre-commit ; extra == 'dev'
Requires-Dist: requests ; extra == 'dev'
